bubbletree/__init__.py
bubbletree/bubbletree.py
bubbletree-1.2.data/scripts/bubbletree.py
bubbletree-1.2.dist-info/LICENSE
bubbletree-1.2.dist-info/METADATA
bubbletree-1.2.dist-info/WHEEL
bubbletree-1.2.dist-info/top_level.txt
bubbletree-1.2.dist-info/RECORD
