Metadata-Version: 2.1
Name: bubbletree
Version: 1.2
Summary: Bubble plot or heatmap ordered by phylogenetic tree
Home-page: https://github.com/aemann01/bubbleTree
Author: Allison E. Mann
Author-email: amann3@clemson.edu
License: UNKNOWN
Platform: UNKNOWN
Classifier: Programming Language :: Python :: 3
Classifier: License :: OSI Approved :: GNU General Public License (GPL)
Classifier: Operating System :: OS Independent
License-File: LICENSE
